{"name":"Thầy Ơi Hôn Cái Nào","folder":"thayoihoncainao","tacGia":"Vị Ương","theLoai":"Ngôn Tình","trangThai":"Full","description":"Tên truyện: Thầy ơi hôn cái nào<br><br>Tác giả: Vị Ương<br><br>Thể loại: ngôn tình, hiện đại, truyện ngọt, vườn trường, 1v1, HE<br><br>Số chương: 08 chương<br><br>Chuyển ngữ: Thanh Ninh<br><br>- Edit: yyds<br><br>- Beta: Amin<br><br>GIỚI THIỆU TÓM TẮT<br><br>“Anh đẹp trai ơi, hôn một cái.”<br><br>“Không…”<br><br>Tôi ôm cổ người đàn ông rồi hôn lên, bạn trai cũ tức giận dẫn tình nhân rời đi.<br><br>Sáng hôm sau, người đàn ông bị tôi cưỡng hôn đứng trên bục giảng, khí chất cao quý, vẻ mặt lạnh lùng.<br><br>“Tự giới thiệu một chút, tôi là giáo viên môn luật hình sự kỳ này của các bạn, Lục Tần.”"}